<list>
  <group>
    <name>test876425133</name>
    <footer>test128236136</footer>
    <header>test464875165</header>
  </group>
  <group>
    <name>test256028021</name>
    <footer></footer>
    <header>test417947377</header>
  </group>
  <group>
    <name></name>
    <footer></footer>
    <header></header>
  </group>
  <group>
    <name>test155541167</name>
    <footer>test827634515</footer>
    <header></header>
  </group>
  <group>
    <name>test12631058</name>
    <footer></footer>
    <header></header>
  </group>
  <group>
    <name></name>
    <footer>test771453942</footer>
    <header>test471991545</header>
  </group>
  <group>
    <name>test446484527</name>
    <footer></footer>
    <header>test513342357</header>
  </group>
  <group>
    <name></name>
    <footer>test668555167</footer>
    <header>test869029316</header>
  </group>
  <group>
    <name></name>
    <footer></footer>
    <header>test404427971</header>
  </group>
  <group>
    <name></name>
    <footer>test326954382</footer>
    <header></header>
  </group>
</list>